encosy/VERSION
encosy/__init__.py
encosy/controlpanel.py
encosy/runner/__init__.py
encosy/runner/meta.py
encosy/runner/runner.py
encosy/storage/__init__.py
encosy/storage/entity_storage.py
encosy/storage/meta.py
encosy/storage/resource_storage.py
encosy/storage/system_storage.py
encosy/storage/typings.py
encosy-3.0.0.dist-info/METADATA
encosy-3.0.0.dist-info/WHEEL
encosy-3.0.0.dist-info/LICENSE
encosy-3.0.0.dist-info/RECORD
