Metadata-Version: 2.1
Name: encosy
Version: 3.0.0
Summary: ECS python implementation
Author: Cruxyu
Author-email: a.kovalenko.ai@gmail.com
Requires-Python: >=3.10,<4.0
Classifier: Programming Language :: Python :: 3
Classifier: Programming Language :: Python :: 3.10
Classifier: Programming Language :: Python :: 3.11
Requires-Dist: mkdocstrings (>=0.19.1,<0.20.0)
